chula
